pragma_sdk/__init__.py
pragma_sdk/auth.py
pragma_sdk/client.py
pragma_sdk/config.py
pragma_sdk/context.py
pragma_sdk/exceptions.py
pragma_sdk/models/__init__.py
pragma_sdk/models/api.py
pragma_sdk/models/base.py
pragma_sdk/models/enums.py
pragma_sdk/models/references.py
pragma_sdk/platform.py
pragma_sdk/provider/__init__.py
pragma_sdk/provider/discovery.py
pragma_sdk/provider/extract_schemas.py
pragma_sdk/provider/harness.py
pragma_sdk/provider/provider.py
pragma_sdk/provider/py.typed
pragma_sdk/py.typed
pragma_sdk/types.py
pragmatiks_sdk-0.18.0.dist-info/WHEEL
pragmatiks_sdk-0.18.0.dist-info/METADATA
pragmatiks_sdk-0.18.0.dist-info/RECORD
