Metadata-Version: 2.3
Name: pragmatiks-sdk
Version: 0.18.0
Summary: Python SDK for the Pragmatiks platform
Classifier: Development Status :: 3 - Alpha
Classifier: Intended Audience :: Developers
Classifier: Programming Language :: Python :: 3.13
Classifier: Typing :: Typed
Requires-Dist: httpx>=0.28.1
Requires-Dist: pydantic>=2.11.4
Requires-Dist: pyyaml>=6.0
Requires-Dist: structlog>=24.1.0
Requires-Python: >=3.13
